paysage/__init__.py
paysage/constraints.py
paysage/optimizers.py
paysage/penalties.py
paysage/preprocess.py
paysage/samplers.py
paysage/schedules.py
paysage-0.2.0.dist-info/METADATA
paysage-0.2.0.dist-info/RECORD
paysage-0.2.0.dist-info/WHEEL
paysage-0.2.0.dist-info/top_level.txt
