Metadata-Version: 2.1
Name: paysage
Version: 0.2.0
Summary: Machine learning with energy based models in python
Home-page: https://github.com/drckf/paysage
Author: Unlearn.AI
Author-email: drckf@unlearn.ai
License: MIT
Platform: UNKNOWN
Classifier: Development Status :: 4 - Beta
Classifier: Intended Audience :: Science/Research
Classifier: Topic :: Scientific/Engineering :: Artificial Intelligence
Classifier: Topic :: Scientific/Engineering :: Physics
Classifier: License :: OSI Approved :: MIT License
Classifier: Programming Language :: Python :: 3.6
Requires-Python: >=3.6
Requires-Dist: matplotlib
Requires-Dist: numexpr
Requires-Dist: numpy
Requires-Dist: pandas
Requires-Dist: pytest
Requires-Dist: scipy
Requires-Dist: seaborn
Requires-Dist: tables
Requires-Dist: torchvision
Requires-Dist: cytoolz
